[
  {
    "nodeType": "WpPage",
    "id": "page-1",
    "uri": "/",
    "title": "Home",
    "content": "<p>Welcome to Missie Tumor Onbekend. We strive to improve care, information, and groundbreaking research for patients with metastatic cancer of unknown primary origin (CUP).</p>",
    "heroSmall": {
      "title": "Missie Tumor Onbekend",
      "subtitle": "Steun ons werk",
      "description": "Help ons om patiënten met kanker van onbekende oorsprong te helpen",
      "image": {
        "localFile": {
          "childImageSharp": {
            "gatsbyImageData": {
              "layout": "constrained",
              "backgroundColor": "#f8f8f8",
              "images": {
                "fallback": {
                  "src": "/static/hero-small-1.jpg",
                  "srcSet": "/static/hero-small-1.jpg 1x",
                  "sizes": "(min-width: 1400px) 1400px, 100vw"
                },
                "sources": [
                  {
                    "srcSet": "/static/hero-small-1.webp 1x",
                    "type": "image/webp",
                    "sizes": "(min-width: 1400px) 1400px, 100vw"
                  }
                ]
              },
              "width": 1400,
              "height": 700
            }
          }
        }
      }
    },
    "hero": {
      "title": "Steun Missie Tumor Onbekend",
      "subtitle": "Help ons om patiënten met kanker van onbekende oorsprong te helpen",
      "description": "Missie Tumor Onbekend zet zich in voor betere toegang tot zorg, informatie en baanbrekend onderzoek voor patiënten met uitgezaaide kanker van een onbekende primaire tumor (PTO).",
      "image": {
        "localFile": {
          "childImageSharp": {
            "gatsbyImageData": {
              "layout": "constrained",
              "backgroundColor": "#f8f8f8",
              "images": {
                "fallback": {
                  "src": "/static/hero-1.jpg",
                  "srcSet": "/static/hero-1.jpg 1x",
                  "sizes": "(min-width: 1400px) 1400px, 100vw"
                },
                "sources": [
                  {
                    "srcSet": "/static/hero-1.webp 1x",
                    "type": "image/webp",
                    "sizes": "(min-width: 1400px) 1400px, 100vw"
                  }
                ]
              },
              "width": 1400,
              "height": 700
            }
          }
        }
      }
    },
    "listOfProjects": {
      "projecta": {
        "title": "Informatievoorziening & bewustwording",
        "description": "Primaire tumor onbekend is een relatief onbekende kankerdiagnose, juist omdat er geen complete diagnose gegeven kan worden. Echter hebben deze mensen wel te maken met uitgezaaide kanker. Missie Tumor Onbekend wil graag dat alle patiënten, naasten, zorgverleners en onderzoekers goed op de hoogte blijven van de laatste kennis en vooruitgang, en ontwikkelt materialen ten behoeve hiervan. Daarnaast werkt Missie Tumor Onbekend ook aan bredere maatschappelijke awareness en bewustwording, zodat PTO-patiënten zich meer gesteund voelen. Meer bekendheid creëert ook nieuwe mogelijkheden om meer projecten voor PTO-patiënten te realiseren.",
        "buttontitle": "Steun dit project",
        "target": 25000,
        "progress": 15000,
        "pagelink": {
          "uri": "/informatievoorziening-bewustwording"
        },
        "image": {
          "localFile": {
            "childImageSharp": {
              "gatsbyImageData": {
                "layout": "constrained",
                "backgroundColor": "#f8f8f8",
                "images": {
                  "fallback": {
                    "src": "/static/project-a.jpg",
                    "srcSet": "/static/project-a.jpg 1x",
                    "sizes": "(min-width: 600px) 600px, 100vw"
                  },
                  "sources": [
                    {
                      "srcSet": "/static/project-a.webp 1x",
                      "type": "image/webp",
                      "sizes": "(min-width: 600px) 600px, 100vw"
                    }
                  ]
                },
                "width": 600,
                "height": 400
              }
            }
          }
        }
      },
      "projectb": {
        "title": "Ondersteunen van wetenschappelijk onderzoek",
        "description": "Missie Tumor Onbekend steunt wetenschappers en zorgverleners graag in relevante onderzoeken naar betere diagnostiek, geneesmiddelen, tumorgerichte behandelingen en palliatieve zorg voor een onbekende primaire tumor. Door nieuwe inzichten kan de schrijnende lage overleving van een PTO verbeteren en de kwaliteit van leven voor de patiënt vooruit. Daarnaast neemt Missie Tumor Onbekend ook zelf het voortouw in het bijeenbrengen van coalities om gezamenlijk wetenschappelijk onderzoek uit te voeren dat in het belang van de PTO-patiënt is. Bij het beoordelen van wetenschappelijk onderzoeksvoorstellen krijgt Missie Tumor Onbekend steun van CUPP-NL, de landelijke beroepsvereniging met expertise over PTO.",
        "buttontitle": "Steun dit project",
        "target": 100000,
        "progress": 25000,
        "pagelink": {
          "uri": "/ondersteunen-van-wetenschappelijk-onderzoek"
        },
        "image": {
          "localFile": {
            "childImageSharp": {
              "gatsbyImageData": {
                "layout": "constrained",
                "backgroundColor": "#f8f8f8",
                "images": {
                  "fallback": {
                    "src": "/static/project-b.jpg",
                    "srcSet": "/static/project-b.jpg 1x",
                    "sizes": "(min-width: 600px) 600px, 100vw"
                  },
                  "sources": [
                    {
                      "srcSet": "/static/project-b.webp 1x",
                      "type": "image/webp",
                      "sizes": "(min-width: 600px) 600px, 100vw"
                    }
                  ]
                },
                "width": 600,
                "height": 400
              }
            }
          }
        }
      },
      "projectc": {
        "title": "Verbetering inzet zorg",
        "description": "Momenteel wordt twee-derde van de PTO-patiënten niet behandeld. Missie Tumor Onbekend werkt samen met zorgverleners hard aan het vergroten van de toegang tot diagnostiek, tumorgerichte behandelingen, palliatieve zorg en psychosociale steun. Missie Tumor Onbekend is betrokken bij de inrichting van het landelijke zorgpad voor PTO en vernieuwingen van de landelijke klinische richtlijn, en steunt projecten die de implementatie en inzet hiervan vergroten.",
        "buttontitle": "Steun dit project",
        "target": 75000,
        "progress": 30000,
        "pagelink": {
          "uri": "/verbetering-inzet-zorg"
        },
        "image": {
          "localFile": {
            "childImageSharp": {
              "gatsbyImageData": {
                "layout": "constrained",
                "backgroundColor": "#f8f8f8",
                "images": {
                  "fallback": {
                    "src": "/static/project-c.jpg",
                    "srcSet": "/static/project-c.jpg 1x",
                    "sizes": "(min-width: 600px) 600px, 100vw"
                  },
                  "sources": [
                    {
                      "srcSet": "/static/project-c.webp 1x",
                      "type": "image/webp",
                      "sizes": "(min-width: 600px) 600px, 100vw"
                    }
                  ]
                },
                "width": 600,
                "height": 400
              }
            }
          }
        }
      }
    },
    "videoSection": {
      "introductiontext": "Onze ambitie is om PTO in 10 jaar tijd de wereld uit te hebben. Daarnaast willen wij ernaar streven dat voor alle PTO-patiënten er effectieve, betaalbare en toegankelijke curatieve en palliatieve behandelingen bestaan.",
      "videolink": {
        "url": "https://www.youtube.com/watch?v=example",
        "target": "_blank",
        "title": "Bekijk de video"
      }
    },
    "patientstoriesimages": {
      "altText": "Patiëntenverhalen",
      "localFile": {
        "childImageSharp": {
          "gatsbyImageData": {
            "layout": "constrained",
            "backgroundColor": "#f8f8f8",
            "images": {
              "fallback": {
                "src": "/static/patient-stories.jpg",
                "srcSet": "/static/patient-stories.jpg 1x",
                "sizes": "(min-width: 800px) 800px, 100vw"
              },
              "sources": [
                {
                  "srcSet": "/static/patient-stories.webp 1x",
                  "type": "image/webp",
                  "sizes": "(min-width: 800px) 800px, 100vw"
                }
              ]
            },
            "width": 800,
            "height": 600
          }
        }
      }
    }
  },
  {
    "nodeType": "WpPage",
    "id": "page-2",
    "uri": "/about",
    "title": "Over Ons",
    "content": "<p>Missie Tumor Onbekend is een organisatie die zich inzet voor patiënten met kanker van onbekende oorsprong. Lees meer over onze missie en visie.</p>",
    "heroSmall": {
      "title": "Over Missie Tumor Onbekend",
      "subtitle": "Onze missie",
      "description": "Leer meer over onze organisatie en wat we doen",
      "image": {
        "localFile": {
          "childImageSharp": {
            "gatsbyImageData": {
              "layout": "constrained",
              "backgroundColor": "#f8f8f8",
              "images": {
                "fallback": {
                  "src": "/static/hero-small-2.jpg",
                  "srcSet": "/static/hero-small-2.jpg 1x",
                  "sizes": "(min-width: 1400px) 1400px, 100vw"
                },
                "sources": [
                  {
                    "srcSet": "/static/hero-small-2.webp 1x",
                    "type": "image/webp",
                    "sizes": "(min-width: 1400px) 1400px, 100vw"
                  }
                ]
              },
              "width": 1400,
              "height": 700
            }
          }
        }
      }
    }
  },
  {
    "nodeType": "WpPage",
    "id": "page-3",
    "uri": "/donate",
    "title": "Doneer",
    "content": "<p>Steun ons werk door te doneren. Uw bijdrage helpt ons om patiënten met kanker van onbekende oorsprong te ondersteunen.</p>",
    "hero": {
      "title": "Doneer aan Missie Tumor Onbekend",
      "subtitle": "Steun ons werk",
      "description": "Uw donatie helpt ons om patiënten met PTO te ondersteunen",
      "image": {
        "localFile": {
          "childImageSharp": {
            "gatsbyImageData": {
              "layout": "constrained",
              "backgroundColor": "#f8f8f8",
              "images": {
                "fallback": {
                  "src": "/static/hero-3.jpg",
                  "srcSet": "/static/hero-3.jpg 1x",
                  "sizes": "(min-width: 1400px) 1400px, 100vw"
                },
                "sources": [
                  {
                    "srcSet": "/static/hero-3.webp 1x",
                    "type": "image/webp",
                    "sizes": "(min-width: 1400px) 1400px, 100vw"
                  }
                ]
              },
              "width": 1400,
              "height": 700
            }
          }
        }
      }
    },
    "listOfProjects": {
      "projecta": {
        "title": "Informatievoorziening & bewustwording",
        "description": "Primaire tumor onbekend is een relatief onbekende kankerdiagnose, juist omdat er geen complete diagnose gegeven kan worden. Echter hebben deze mensen wel te maken met uitgezaaide kanker. Missie Tumor Onbekend wil graag dat alle patiënten, naasten, zorgverleners en onderzoekers goed op de hoogte blijven van de laatste kennis en vooruitgang, en ontwikkelt materialen ten behoeve hiervan. Daarnaast werkt Missie Tumor Onbekend ook aan bredere maatschappelijke awareness en bewustwording, zodat PTO-patiënten zich meer gesteund voelen. Meer bekendheid creëert ook nieuwe mogelijkheden om meer projecten voor PTO-patiënten te realiseren.",
        "buttontitle": "Steun dit project",
        "target": 15000,
        "progress": 8500,
        "pagelink": {
          "uri": "/informatievoorziening-bewustwording"
        },
        "image": {
          "localFile": {
            "childImageSharp": {
              "gatsbyImageData": {
                "layout": "constrained",
                "backgroundColor": "#f8f8f8",
                "images": {
                  "fallback": {
                    "src": "/static/project-a.jpg",
                    "srcSet": "/static/project-a.jpg 1x",
                    "sizes": "(min-width: 600px) 600px, 100vw"
                  },
                  "sources": [
                    {
                      "srcSet": "/static/project-a.webp 1x",
                      "type": "image/webp",
                      "sizes": "(min-width: 600px) 600px, 100vw"
                    }
                  ]
                },
                "width": 600,
                "height": 400
              }
            }
          }
        }
      },
      "projectb": {
        "title": "Ondersteunen van wetenschappelijk onderzoek",
        "description": "Missie Tumor Onbekend steunt wetenschappers en zorgverleners graag in relevante onderzoeken naar betere diagnostiek, geneesmiddelen, tumorgerichte behandelingen en palliatieve zorg voor een onbekende primaire tumor. Door nieuwe inzichten kan de schrijnende lage overleving van een PTO verbeteren en de kwaliteit van leven voor de patiënt vooruit. Daarnaast neemt Missie Tumor Onbekend ook zelf het voortouw in het bijeenbrengen van coalities om gezamenlijk wetenschappelijk onderzoek uit te voeren dat in het belang van de PTO-patiënt is. Bij het beoordelen van wetenschappelijk onderzoeksvoorstellen krijgt Missie Tumor Onbekend steun van CUPP-NL, de landelijke beroepsvereniging met expertise over PTO.",
        "buttontitle": "Steun dit project",
        "target": 15000,
        "progress": 8000,
        "pagelink": {
          "uri": "/ondersteunen-van-wetenschappelijk-onderzoek"
        },
        "image": {
          "localFile": {
            "childImageSharp": {
              "gatsbyImageData": {
                "layout": "constrained",
                "backgroundColor": "#f8f8f8",
                "images": {
                  "fallback": {
                    "src": "/static/project-b.jpg",
                    "srcSet": "/static/project-b.jpg 1x",
                    "sizes": "(min-width: 600px) 600px, 100vw"
                  },
                  "sources": [
                    {
                      "srcSet": "/static/project-b.webp 1x",
                      "type": "image/webp",
                      "sizes": "(min-width: 600px) 600px, 100vw"
                    }
                  ]
                },
                "width": 600,
                "height": 400
              }
            }
          }
        }
      },
      "projectc": {
        "title": "Verbetering inzet zorg",
        "description": "Momenteel wordt twee-derde van de PTO-patiënten niet behandeld. Missie Tumor Onbekend werkt samen met zorgverleners hard aan het vergroten van de toegang tot diagnostiek, tumorgerichte behandelingen, palliatieve zorg en psychosociale steun. Missie Tumor Onbekend is betrokken bij de inrichting van het landelijke zorgpad voor PTO en vernieuwingen van de landelijke klinische richtlijn, en steunt projecten die de implementatie en inzet hiervan vergroten.",
        "buttontitle": "Steun dit project",
        "target": 20000,
        "progress": 12000,
        "pagelink": {
          "uri": "/verbetering-inzet-zorg"
        },
        "image": {
          "localFile": {
            "childImageSharp": {
              "gatsbyImageData": {
                "layout": "constrained",
                "backgroundColor": "#f8f8f8",
                "images": {
                  "fallback": {
                    "src": "/static/project-c.jpg",
                    "srcSet": "/static/project-c.jpg 1x",
                    "sizes": "(min-width: 600px) 600px, 100vw"
                  },
                  "sources": [
                    {
                      "srcSet": "/static/project-c.webp 1x",
                      "type": "image/webp",
                      "sizes": "(min-width: 600px) 600px, 100vw"
                    }
                  ]
                },
                "width": 600,
                "height": 400
              }
            }
          }
        }
      }
    },
    "videoSection": {
      "introductiontext": "Bekijk onze introductievideo om meer te leren over Missie Tumor Onbekend.",
      "videolink": {
        "url": "https://www.youtube.com/watch?v=example",
        "target": "_blank",
        "title": "Bekijk de video"
      }
    },
    "patientstoriesimages": {
      "altText": "Patiëntenverhalen",
      "localFile": {
        "childImageSharp": {
          "gatsbyImageData": {
            "layout": "constrained",
            "backgroundColor": "#f8f8f8",
            "images": {
              "fallback": {
                "src": "/static/patient-stories.jpg",
                "srcSet": "/static/patient-stories.jpg 1x",
                "sizes": "(min-width: 800px) 800px, 100vw"
              },
              "sources": [
                {
                  "srcSet": "/static/patient-stories.webp 1x",
                  "type": "image/webp",
                  "sizes": "(min-width: 800px) 800px, 100vw"
                }
              ]
            },
            "width": 800,
            "height": 600
          }
        }
      }
    }
  },
  {
    "nodeType": "WpPage",
    "id": "page-4",
    "uri": "/informatievoorziening-bewustwording",
    "title": "Informatievoorziening & bewustwording",
    "heroSmall": {
      "title": "Informatievoorziening & bewustwording",
      "subtitle": "Verbeteren van kennis en bewustwording",
      "description": "Leer meer over onze informatievoorziening en bewustwordingscampagnes"
    },
    "projectProgress": {
      "progressie": 15000,
      "target": 25000
    },
    "hero": {
      "title": "Informatievoorziening & bewustwording",
      "subtitle": "Verbeteren van kennis en bewustwording",
      "description": "Leer meer over onze informatievoorziening en bewustwordingscampagnes",
      "image": {
        "localFile": {
          "childImageSharp": {
            "gatsbyImageData": {
              "layout": "constrained",
              "backgroundColor": "#f8f8f8",
              "images": {
                "fallback": {
                  "src": "/static/hero-4.jpg",
                  "srcSet": "/static/hero-4.jpg 1x",
                  "sizes": "(min-width: 1400px) 1400px, 100vw"
                },
                "sources": [
                  {
                    "srcSet": "/static/hero-4.webp 1x",
                    "type": "image/webp",
                    "sizes": "(min-width: 1400px) 1400px, 100vw"
                  }
                ]
              },
              "width": 1400,
              "height": 700
            }
          }
        }
      }
    },
    "project": {
      "projectimage": {
        "localFile": {
          "childImageSharp": {
            "gatsbyImageData": {
              "layout": "constrained",
              "backgroundColor": "#f8f8f8",
              "images": {
                "fallback": {
                  "src": "/static/project-a-large.jpg",
                  "srcSet": "/static/project-a-large.jpg 1x",
                  "sizes": "(min-width: 800px) 800px, 100vw"
                },
                "sources": [
                  {
                    "srcSet": "/static/project-a-large.webp 1x",
                    "type": "image/webp",
                    "sizes": "(min-width: 800px) 800px, 100vw"
                  }
                ]
              },
              "width": 800,
              "height": 600
            }
          }
        }
      }
    }
  },
  {
    "nodeType": "WpPage",
    "id": "page-5",
    "uri": "/ondersteunen-van-wetenschappelijk-onderzoek",
    "title": "Ondersteunen van wetenschappelijk onderzoek",
    "content": "",
    "heroSmall": {
      "title": "Ondersteunen van wetenschappelijk onderzoek",
      "subtitle": "Innovatief onderzoek naar PTO",
      "description": "Leer meer over ons wetenschappelijk onderzoek naar PTO",
      "image": {
        "localFile": {
          "childImageSharp": {
            "gatsbyImageData": {
              "layout": "constrained",
              "backgroundColor": "#f8f8f8",
              "images": {
                "fallback": {
                  "src": "/static/hero-small-5.jpg",
                  "srcSet": "/static/hero-small-5.jpg 1x",
                  "sizes": "(min-width: 1400px) 1400px, 100vw"
                },
                "sources": [
                  {
                    "srcSet": "/static/hero-small-5.webp 1x",
                    "type": "image/webp",
                    "sizes": "(min-width: 1400px) 1400px, 100vw"
                  }
                ]
              },
              "width": 1400,
              "height": 700
            }
          }
        }
      }
    },
    "projectProgress": {
      "progressie": 25000,
      "target": 100000
    },
    "hero": {
      "title": "Ondersteunen van wetenschappelijk onderzoek",
      "subtitle": "Innovatief onderzoek naar PTO",
      "description": "Leer meer over ons wetenschappelijk onderzoek naar PTO",
      "image": {
        "localFile": {
          "childImageSharp": {
            "gatsbyImageData": {
              "layout": "constrained",
              "backgroundColor": "#f8f8f8",
              "images": {
                "fallback": {
                  "src": "/static/hero-5.jpg",
                  "srcSet": "/static/hero-5.jpg 1x",
                  "sizes": "(min-width: 1400px) 1400px, 100vw"
                },
                "sources": [
                  {
                    "srcSet": "/static/hero-5.webp 1x",
                    "type": "image/webp",
                    "sizes": "(min-width: 1400px) 1400px, 100vw"
                  }
                ]
              },
              "width": 1400,
              "height": 700
            }
          }
        }
      }
    }
  },
  {
    "nodeType": "WpPage",
    "id": "page-6",
    "uri": "/verbetering-inzet-zorg",
    "title": "Verbetering inzet zorg",
    "content": "<p>Het project Verbetering Inzet Zorg richt zich op het optimaliseren van zorgprocessen en behandelprotocollen voor patiënten met Primaire Tumor Onbekend (PTO).</p><p>Onze doelstellingen zijn:</p><ul><li>Het verbeteren van de coördinatie tussen verschillende zorgverleners</li><li>Het ontwikkelen van gespecialiseerde zorgpaden voor PTO-patiënten</li><li>Het verkorten van de tijd tussen diagnose en behandeling</li><li>Het verbeteren van de kwaliteit van leven tijdens en na behandeling</li></ul><p>Met uw steun kunnen we de zorg voor PTO-patiënten substantieel verbeteren.</p>",
    "heroSmall": {
      "title": "Verbetering inzet zorg",
      "subtitle": "Optimalisatie van zorgprocessen",
      "description": "Leer meer over onze initiatieven voor betere zorg bij PTO"
    },
    "projectProgress": {
      "progressie": 30000,
      "target": 75000
    },
    "hero": {
      "title": "Verbetering inzet zorg",
      "subtitle": "Optimalisatie van zorgprocessen",
      "description": "Leer meer over onze initiatieven voor betere zorg bij PTO"
    }
  },
  {
    "nodeType": "WpPage",
    "id": "page-7",
    "uri": "/bedankt-voor-uw-donatie",
    "title": "Bedankt voor uw donatie",
    "content": "<h1>Bedankt voor uw donatie</h1>\n<p>Hartelijk dank voor uw genereuze bijdrage aan Missie Tumor Onbekend. Uw steun helpt ons om patiënten met kanker van onbekende oorsprong te helpen.</p>\n<p>Dankzij donaties zoals die van u kunnen wij ons blijven inzetten voor:</p>\n<ul>\n<li>Betere informatievoorziening voor patiënten en hun naasten</li>\n<li>Het ondersteunen van wetenschappelijk onderzoek naar betere diagnostiek en behandelingen</li>\n<li>Het verbeteren van de zorg voor patiënten met een primaire tumor onbekend (PTO)</li>\n</ul>\n<p>Uw bijdrage maakt echt verschil in het leven van mensen die getroffen zijn door deze zeldzame en complexe vorm van kanker.</p>\n<p>Heeft u vragen over uw donatie of wilt u meer informatie over ons werk? Neem dan gerust contact met ons op.</p>",
    "heroSmall": {
      "title": "Bedankt voor uw donatie",
      "subtitle": "Uw steun is van onschatbare waarde",
      "description": "Samen maken we het verschil voor patiënten met kanker van onbekende oorsprong",
      "image": {
        "localFile": {
          "childImageSharp": {
            "gatsbyImageData": {
              "layout": "constrained",
              "backgroundColor": "#f8f8f8",
              "images": {
                "fallback": {
                  "src": "/static/hero-small-1.jpg",
                  "srcSet": "/static/hero-small-1.jpg 1x",
                  "sizes": "(min-width: 1400px) 1400px, 100vw"
                },
                "sources": [
                  {
                    "srcSet": "/static/hero-small-1.webp 1x",
                    "type": "image/webp",
                    "sizes": "(min-width: 1400px) 1400px, 100vw"
                  }
                ]
              },
              "width": 1400,
              "height": 700
            }
          }
        }
      }
    }
  },
  {
    "nodeType": "WpPage",
    "id": "page-8",
    "uri": "/privacy-cookie-verklaring",
    "title": "Privacy & cookie verklaring",
    "content": "<h1>Privacy & cookie verklaring</h1>\n<p>Bij Missie Tumor Onbekend hechten wij grote waarde aan de privacy van onze websitebezoekers en donateurs. In deze verklaring leggen wij uit welke gegevens wij verzamelen, waarom wij deze verzamelen en hoe wij deze gebruiken.</p>\n<h2>Persoonsgegevens die wij verwerken</h2>\n<p>Missie Tumor Onbekend verwerkt uw persoonsgegevens wanneer u gebruik maakt van onze diensten en/of wanneer u deze zelf aan ons verstrekt. Hieronder vindt u een overzicht van de persoonsgegevens die wij verwerken:</p>\n<ul>\n<li>Voor- en achternaam</li>\n<li>Adresgegevens</li>\n<li>Telefoonnummer</li>\n<li>E-mailadres</li>\n<li>Bankrekeningnummer (in geval van donaties)</li>\n</ul>\n<h2>Cookies</h2>\n<p>Missie Tumor Onbekend gebruikt alleen technische, functionele en analytische cookies die geen inbreuk maken op uw privacy. Een cookie is een klein tekstbestand dat bij het eerste bezoek aan deze website wordt opgeslagen op uw computer, tablet of smartphone. De cookies die wij gebruiken zijn noodzakelijk voor de technische werking van de website en uw gebruiksgemak.</p>\n<h2>Wijzigingen in deze verklaring</h2>\n<p>Wij behouden ons het recht voor om wijzigingen aan te brengen in deze privacyverklaring. Het verdient aanbeveling om deze privacyverklaring geregeld te raadplegen, zodat u van deze wijzigingen op de hoogte bent.</p>",
    "heroSmall": {
      "title": "Privacy & cookie verklaring",
      "subtitle": "Hoe wij omgaan met uw gegevens",
      "description": "Transparantie en zorgvuldigheid staan voorop bij het verwerken van uw persoonsgegevens",
      "image": {
        "localFile": {
          "childImageSharp": {
            "gatsbyImageData": {
              "layout": "constrained",
              "backgroundColor": "#f8f8f8",
              "images": {
                "fallback": {
                  "src": "/static/hero-small-1.jpg",
                  "srcSet": "/static/hero-small-1.jpg 1x",
                  "sizes": "(min-width: 1400px) 1400px, 100vw"
                },
                "sources": [
                  {
                    "srcSet": "/static/hero-small-1.webp 1x",
                    "type": "image/webp",
                    "sizes": "(min-width: 1400px) 1400px, 100vw"
                  }
                ]
              },
              "width": 1400,
              "height": 700
            }
          }
        }
      }
    }
  },
  {
    "nodeType": "WpPage",
    "id": "page-9",
    "uri": "/fondsenwervingsbeleid",
    "title": "Fondsenwervingsbeleid",
    "content": "<h1>Fondsenwervingsbeleid</h1>\n<p>Missie Tumor Onbekend zet zich in voor patiënten met kanker van onbekende oorsprong. Om onze doelstellingen te bereiken, werven wij fondsen via verschillende kanalen. In dit beleidsdocument leggen wij uit hoe wij dit doen.</p>\n<h2>Onze uitgangspunten</h2>\n<p>Bij onze fondsenwerving hanteren wij de volgende uitgangspunten:</p>\n<ul>\n<li>Transparantie: wij zijn open over hoe wij fondsen werven en besteden</li>\n<li>Integriteit: wij gaan zorgvuldig om met donaties en respecteren de wensen van donateurs</li>\n<li>Efficiëntie: wij streven ernaar de kosten voor fondsenwerving zo laag mogelijk te houden</li>\n<li>Doelgerichtheid: alle geworven fondsen komen ten goede aan onze missie</li>\n</ul>\n<h2>Methoden van fondsenwerving</h2>\n<p>Wij werven fondsen via de volgende methoden:</p>\n<ul>\n<li>Donaties van particulieren (eenmalig of periodiek)</li>\n<li>Donaties van bedrijven en instellingen</li>\n<li>Subsidies van overheden en fondsen</li>\n<li>Evenementen en acties</li>\n<li>Nalatenschappen</li>\n</ul>\n<h2>Besteding van fondsen</h2>\n<p>De geworven fondsen worden besteed aan:</p>\n<ul>\n<li>Informatievoorziening & bewustwording</li>\n<li>Ondersteunen van wetenschappelijk onderzoek</li>\n<li>Verbetering inzet zorg</li>\n<li>Organisatiekosten (maximaal 15% van de totale inkomsten)</li>\n</ul>\n<p>Jaarlijks leggen wij verantwoording af over de besteding van de fondsen in ons jaarverslag.</p>",
    "heroSmall": {
      "title": "Fondsenwervingsbeleid",
      "subtitle": "Hoe wij fondsen werven en besteden",
      "description": "Transparantie en integriteit staan centraal bij onze fondsenwerving",
      "image": {
        "localFile": {
          "childImageSharp": {
            "gatsbyImageData": {
              "layout": "constrained",
              "backgroundColor": "#f8f8f8",
              "images": {
                "fallback": {
                  "src": "/static/hero-small-1.jpg",
                  "srcSet": "/static/hero-small-1.jpg 1x",
                  "sizes": "(min-width: 1400px) 1400px, 100vw"
                },
                "sources": [
                  {
                    "srcSet": "/static/hero-small-1.webp 1x",
                    "type": "image/webp",
                    "sizes": "(min-width: 1400px) 1400px, 100vw"
                  }
                ]
              },
              "width": 1400,
              "height": 700
            }
          }
        }
      }
    }
  }
]
